reading_machine/__init__.py
reading_machine/githf.py
reading_machine/machina.yaml
reading_machine-0.0.1.dist-info/LICENSE
reading_machine-0.0.1.dist-info/METADATA
reading_machine-0.0.1.dist-info/WHEEL
reading_machine-0.0.1.dist-info/top_level.txt
reading_machine-0.0.1.dist-info/RECORD
